Anuvaad_Tokenizer/AnuvaadEnTokenizer.py
Anuvaad_Tokenizer/AnuvaadHiTokenizer.py
Anuvaad_Tokenizer/AnuvaadKnTokenizer.py
Anuvaad_Tokenizer/AnuvaadTaTokenizer.py
Anuvaad_Tokenizer/AnuvaadTeTokenizer.py
Anuvaad_Tokenizer/__init__.py
Anuvaad_Tokenizer-0.0.3.dist-info/METADATA
Anuvaad_Tokenizer-0.0.3.dist-info/WHEEL
Anuvaad_Tokenizer-0.0.3.dist-info/top_level.txt
Anuvaad_Tokenizer-0.0.3.dist-info/RECORD
