Metadata-Version: 2.1
Name: Anuvaad-Tokenizer
Version: 0.0.3
Summary: Tokenizer by Anuvaad 
Home-page: UNKNOWN
Author: Anuvaad
Author-email: nlp-nmt@tarento.com
License: MIT
Platform: UNKNOWN
Classifier: License :: OSI Approved :: MIT License
Classifier: Programming Language :: Python
Requires-Python: >=3.6.0
Requires-Dist: nltk
